fis_data/__init__.py
fis_data/rearrange_fis_data.py
fis_data-0.1.1.dist-info/LICENSE
fis_data-0.1.1.dist-info/METADATA
fis_data-0.1.1.dist-info/WHEEL
fis_data-0.1.1.dist-info/entry_points.txt
fis_data-0.1.1.dist-info/top_level.txt
fis_data-0.1.1.dist-info/RECORD
