Metadata-Version: 2.1
Name: fis-data
Version: 0.1.1
Summary: A package for rearranging FIS data
Home-page: https://github.com/NEbrahimi/fis_data
Author: Naz Ebrahimi
License: MIT
Classifier: License :: OSI Approved :: MIT License
Classifier: Programming Language :: Python :: 3.11
License-File: LICENSE
Requires-Dist: pandas >=1.0.0
Requires-Dist: openpyxl
